<annotation>
	<folder>images3</folder>
	<filename>16-auto23-17.jpg</filename>
	<path>/home/jrodriguez/x/imagenes3/images3/16-auto23-17.jpg</path>
	<source>
		<database>Unknown</database>
	</source>
	<size>
		<width>2061</width>
		<height>1484</height>
		<depth>3</depth>
	</size>
	<segmented>0</segmented>
	<object>
		<name>bridge</name>
		<pose>Unspecified</pose>
		<truncated>0</truncated>
		<difficult>0</difficult>
		<bndbox>
			<xmin>462</xmin>
			<ymin>649</ymin>
			<xmax>479</xmax>
			<ymax>696</ymax>
		</bndbox>
	</object>
	<object>
		<name>bridge</name>
		<pose>Unspecified</pose>
		<truncated>0</truncated>
		<difficult>0</difficult>
		<bndbox>
			<xmin>1250</xmin>
			<ymin>700</ymin>
			<xmax>1288</xmax>
			<ymax>740</ymax>
		</bndbox>
	</object>
	<object>
		<name>motorway</name>
		<pose>Unspecified</pose>
		<truncated>1</truncated>
		<difficult>0</difficult>
		<bndbox>
			<xmin>1</xmin>
			<ymin>667</ymin>
			<xmax>317</xmax>
			<ymax>747</ymax>
		</bndbox>
	</object>
	<object>
		<name>motorway</name>
		<pose>Unspecified</pose>
		<truncated>0</truncated>
		<difficult>0</difficult>
		<bndbox>
			<xmin>319</xmin>
			<ymin>640</ymin>
			<xmax>670</xmax>
			<ymax>712</ymax>
		</bndbox>
	</object>
	<object>
		<name>motorway</name>
		<pose>Unspecified</pose>
		<truncated>0</truncated>
		<difficult>0</difficult>
		<bndbox>
			<xmin>676</xmin>
			<ymin>645</ymin>
			<xmax>1017</xmax>
			<ymax>722</ymax>
		</bndbox>
	</object>
	<object>
		<name>motorway</name>
		<pose>Unspecified</pose>
		<truncated>0</truncated>
		<difficult>0</difficult>
		<bndbox>
			<xmin>1016</xmin>
			<ymin>674</ymin>
			<xmax>1357</xmax>
			<ymax>751</ymax>
		</bndbox>
	</object>
	<object>
		<name>motorway</name>
		<pose>Unspecified</pose>
		<truncated>0</truncated>
		<difficult>0</difficult>
		<bndbox>
			<xmin>1360</xmin>
			<ymin>704</ymin>
			<xmax>1687</xmax>
			<ymax>786</ymax>
		</bndbox>
	</object>
	<object>
		<name>motorway</name>
		<pose>Unspecified</pose>
		<truncated>0</truncated>
		<difficult>0</difficult>
		<bndbox>
			<xmin>1686</xmin>
			<ymin>759</ymin>
			<xmax>1928</xmax>
			<ymax>831</ymax>
		</bndbox>
	</object>
	<object>
		<name>motorway</name>
		<pose>Unspecified</pose>
		<truncated>1</truncated>
		<difficult>0</difficult>
		<bndbox>
			<xmin>1913</xmin>
			<ymin>781</ymin>
			<xmax>2061</xmax>
			<ymax>893</ymax>
		</bndbox>
	</object>
</annotation>
