<annotation>
	<folder>images</folder>
	<filename>puerto3-17.jpg</filename>
	<path>/home/jrodriguez/x/imagenes/images/puerto3-17.jpg</path>
	<source>
		<database>Unknown</database>
	</source>
	<size>
		<width>2027</width>
		<height>1370</height>
		<depth>3</depth>
	</size>
	<segmented>0</segmented>
	<object>
		<name>harbor</name>
		<pose>Unspecified</pose>
		<truncated>0</truncated>
		<difficult>0</difficult>
		<bndbox>
			<xmin>320</xmin>
			<ymin>27</ymin>
			<xmax>878</xmax>
			<ymax>473</ymax>
		</bndbox>
	</object>
	<object>
		<name>motorway</name>
		<pose>Unspecified</pose>
		<truncated>1</truncated>
		<difficult>0</difficult>
		<bndbox>
			<xmin>962</xmin>
			<ymin>1148</ymin>
			<xmax>1130</xmax>
			<ymax>1370</ymax>
		</bndbox>
	</object>
	<object>
		<name>motorway</name>
		<pose>Unspecified</pose>
		<truncated>0</truncated>
		<difficult>0</difficult>
		<bndbox>
			<xmin>744</xmin>
			<ymin>993</ymin>
			<xmax>962</xmax>
			<ymax>1163</ymax>
		</bndbox>
	</object>
	<object>
		<name>motorway</name>
		<pose>Unspecified</pose>
		<truncated>0</truncated>
		<difficult>0</difficult>
		<bndbox>
			<xmin>507</xmin>
			<ymin>849</ymin>
			<xmax>746</xmax>
			<ymax>1017</ymax>
		</bndbox>
	</object>
	<object>
		<name>motorway</name>
		<pose>Unspecified</pose>
		<truncated>0</truncated>
		<difficult>0</difficult>
		<bndbox>
			<xmin>313</xmin>
			<ymin>690</ymin>
			<xmax>513</xmax>
			<ymax>873</ymax>
		</bndbox>
	</object>
	<object>
		<name>motorway</name>
		<pose>Unspecified</pose>
		<truncated>0</truncated>
		<difficult>0</difficult>
		<bndbox>
			<xmin>103</xmin>
			<ymin>511</ymin>
			<xmax>307</xmax>
			<ymax>695</ymax>
		</bndbox>
	</object>
	<object>
		<name>motorway</name>
		<pose>Unspecified</pose>
		<truncated>1</truncated>
		<difficult>0</difficult>
		<bndbox>
			<xmin>1</xmin>
			<ymin>413</ymin>
			<xmax>113</xmax>
			<ymax>514</ymax>
		</bndbox>
	</object>
	<object>
		<name>industrial</name>
		<pose>Unspecified</pose>
		<truncated>0</truncated>
		<difficult>0</difficult>
		<bndbox>
			<xmin>558</xmin>
			<ymin>717</ymin>
			<xmax>748</xmax>
			<ymax>927</ymax>
		</bndbox>
	</object>
</annotation>
