<annotation>
	<folder>images</folder>
	<filename>Badajoz16.jpg</filename>
	<path>/mnt/37EF314C613A76E8/GitHub/x/IMAGENES/Aeropuertos/SASPlanet_Aer_Originales1/images/Badajoz16.jpg</path>
	<source>
		<database>Unknown</database>
	</source>
	<size>
		<width>1857</width>
		<height>1321</height>
		<depth>3</depth>
	</size>
	<segmented>0</segmented>
	<object>
		<name>airport</name>
		<pose>Unspecified</pose>
		<truncated>0</truncated>
		<difficult>0</difficult>
		<bndbox>
			<xmin>624</xmin>
			<ymin>461</ymin>
			<xmax>1393</xmax>
			<ymax>903</ymax>
		</bndbox>
	</object>
	<object>
		<name>motorway</name>
		<pose>Unspecified</pose>
		<truncated>1</truncated>
		<difficult>0</difficult>
		<bndbox>
			<xmin>1</xmin>
			<ymin>1110</ymin>
			<xmax>340</xmax>
			<ymax>1197</ymax>
		</bndbox>
	</object>
	<object>
		<name>motorway</name>
		<pose>Unspecified</pose>
		<truncated>0</truncated>
		<difficult>0</difficult>
		<bndbox>
			<xmin>344</xmin>
			<ymin>1158</ymin>
			<xmax>685</xmax>
			<ymax>1245</ymax>
		</bndbox>
	</object>
	<object>
		<name>motorway</name>
		<pose>Unspecified</pose>
		<truncated>0</truncated>
		<difficult>0</difficult>
		<bndbox>
			<xmin>689</xmin>
			<ymin>1174</ymin>
			<xmax>1029</xmax>
			<ymax>1261</ymax>
		</bndbox>
	</object>
	<object>
		<name>motorway</name>
		<pose>Unspecified</pose>
		<truncated>0</truncated>
		<difficult>0</difficult>
		<bndbox>
			<xmin>1028</xmin>
			<ymin>1216</ymin>
			<xmax>1368</xmax>
			<ymax>1303</ymax>
		</bndbox>
	</object>
	<object>
		<name>motorway</name>
		<pose>Unspecified</pose>
		<truncated>1</truncated>
		<difficult>0</difficult>
		<bndbox>
			<xmin>1367</xmin>
			<ymin>1221</ymin>
			<xmax>1709</xmax>
			<ymax>1321</ymax>
		</bndbox>
	</object>
	<object>
		<name>industrial</name>
		<pose>Unspecified</pose>
		<truncated>0</truncated>
		<difficult>0</difficult>
		<bndbox>
			<xmin>9</xmin>
			<ymin>403</ymin>
			<xmax>140</xmax>
			<ymax>514</ymax>
		</bndbox>
	</object>
</annotation>
