<annotation>
	<folder>images</folder>
	<filename>ParisDeauville18.jpg</filename>
	<path>/mnt/37EF314C613A76E8/GitHub/x/IMAGENES/Aeropuertos/AeropuertosParis/images/ParisDeauville18.jpg</path>
	<source>
		<database>Unknown</database>
	</source>
	<size>
		<width>8233</width>
		<height>4773</height>
		<depth>3</depth>
	</size>
	<segmented>0</segmented>
	<object>
		<name>airport</name>
		<pose>Unspecified</pose>
		<truncated>0</truncated>
		<difficult>0</difficult>
		<bndbox>
			<xmin>3123</xmin>
			<ymin>1858</ymin>
			<xmax>6092</xmax>
			<ymax>3014</ymax>
		</bndbox>
	</object>
</annotation>
